bolt_raycast/__init__.py
bolt_raycast/comment.py
bolt_raycast/enums.py
bolt_raycast/modules/branch_mixin.bolt
bolt_raycast/modules/detect_block.bolt
bolt_raycast/modules/detect_entity.bolt
bolt_raycast/modules/if_new_block_pos.bolt
bolt_raycast/modules/raycast.bolt
bolt_raycast/py.typed
bolt_raycast-0.3.0.dist-info/LICENSE
bolt_raycast-0.3.0.dist-info/WHEEL
bolt_raycast-0.3.0.dist-info/METADATA
bolt_raycast-0.3.0.dist-info/RECORD
